service_collection/__init__.py
service_collection/collections.py
service_collection-0.6.3.dist-info/LICENSE
service_collection-0.6.3.dist-info/METADATA
service_collection-0.6.3.dist-info/WHEEL
service_collection-0.6.3.dist-info/top_level.txt
service_collection-0.6.3.dist-info/RECORD
