Metadata-Version: 2.1
Name: service_collection
Version: 0.6.3
Summary: ASP.NET Core-style dependency injection service collection for Python
Home-page: https://github.com/ameyer117/service_collection
Author: Alec Meyer
Author-email: 11meyal@gmail.com
License: MIT License
Project-URL: Homepage, https://github.com/ameyer117/service_collection
Requires-Python: >=3.9
License-File: LICENSE
